Metadata-Version: 2.1
Name: edenredproxy
Version: 100.5
Summary: Malicious ERBR Package
Author: BONFIM Kaio
